mir/sitemap/__init__.py
mir.sitemap-1.1.0.dist-info/DESCRIPTION.rst
mir.sitemap-1.1.0.dist-info/METADATA
mir.sitemap-1.1.0.dist-info/RECORD
mir.sitemap-1.1.0.dist-info/WHEEL
mir.sitemap-1.1.0.dist-info/metadata.json
mir.sitemap-1.1.0.dist-info/top_level.txt
