Metadata-Version: 2.0
Name: mir.sitemap
Version: 1.1.0
Summary: Sitemap generator
Home-page: https://github.com/darkfeline/mir.sitemap
Author: Allen Li
Author-email: darkfeline@felesatra.moe
License: UNKNOWN
Platform: UNKNOWN
Classifier: Development Status :: 5 - Production/Stable
Classifier: Intended Audience :: Developers
Classifier: License :: OSI Approved :: Apache Software License
Classifier: Programming Language :: Python :: 3.6
Requires-Python: ~=3.6
